webauthin/__init__.py
webauthin/admin.py
webauthin/apps.py
webauthin/auth_backends.py
webauthin/models.py
webauthin/settings.py
webauthin/tests.py
webauthin/urls.py
webauthin/views.py
webauthin/migrations/0001_initial.py
webauthin/migrations/0002_authdata_sign_count.py
webauthin/migrations/0003_auto_20191228_1750.py
webauthin/migrations/0004_auto_20191229_0020.py
webauthin/migrations/0005_authdata_friendly_name.py
webauthin/migrations/0006_auto_20191230_1225.py
webauthin/migrations/__init__.py
webauthin/templates/webauthin_login.html
webauthin/templates/webauthin_register.html
django_webauthin-0.0.6.dist-info/LICENSE
django_webauthin-0.0.6.dist-info/METADATA
django_webauthin-0.0.6.dist-info/WHEEL
django_webauthin-0.0.6.dist-info/top_level.txt
django_webauthin-0.0.6.dist-info/RECORD
