Metadata-Version: 2.1
Name: django-webauthin
Version: 0.0.6
Summary: Passwordless authentication using WebAuthn.
Home-page: https://gitlab.com/stavros/django-webauthin
Author: Stavros Korokithakis
Author-email: hi@stavros.io
License: BSD
Keywords: django
Platform: UNKNOWN
Requires-Python: >=3.6
Requires-Dist: webauthn
